lukhed_sports/__init__.py
lukhed_sports/dkWrapper.py
lukhed_sports/espnWrapper.py
lukhed_sports/gameAnalysis.py
lukhed_sports/leagueData.py
lukhed_sports/nflSchedules.py
lukhed_sports/sportsPageWrapper.py
lukhed_sports/calibrations/__init__.py
lukhed_sports/calibrations/endpoint_valid_inputs.py
lukhed_sports/calibrations/dk/__init__.py
lukhed_sports/calibrations/dk/apiVersions.json
lukhed_sports/calibrations/dk/api_versions.py
lukhed_sports/example_responses/gamelinesForLeague.json
lukhed_sports/example_responses/getGameId.json
lukhed_sports/example_responses/getOddsById.json
lukhed_sports/example_responses/getRankings.json
lukhed_sports/example_responses/mlbConferences.json
lukhed_sports/example_responses/nbaConferences.json
lukhed_sports/example_responses/ncaabConferences.json
lukhed_sports/example_responses/ncaafConferences.json
lukhed_sports/example_responses/ncaafTeams.json
lukhed_sports/example_responses/nflConferences.json
lukhed_sports/example_responses/nflGames.json
lukhed_sports/example_responses/nhlConferences.json
lukhed_sports/local_cache/dk_available_leagues_cache.json
lukhed_sports/local_cache/dk_sports_cache.json
lukhed_sports/translations/majorSportsFull.json
sports_utilities/__init__.py
sports_utilities/gameAnalysis.py
sports_utilities/sportsPageWrapper.py
tests/__init__.py
tests/test_game_analysis.py
lukhed_sports-0.10.2.dist-info/LICENSE
lukhed_sports-0.10.2.dist-info/METADATA
lukhed_sports-0.10.2.dist-info/WHEEL
lukhed_sports-0.10.2.dist-info/top_level.txt
lukhed_sports-0.10.2.dist-info/RECORD
