Metadata-Version: 2.1
Name: lukhed-sports
Version: 0.10.2
Summary: A collection of sports analysis utility functions and API wrappers
Home-page: https://github.com/lukhed/lukhed_sports
Author: lukhed
Author-email: lukhed.mail@gmail.com
Classifier: Programming Language :: Python :: 3
Classifier: License :: OSI Approved :: MIT License
Classifier: Operating System :: OS Independent
Requires-Python: >=3.9
License-File: LICENSE
Requires-Dist: lukhed-basic-utils>=1.5.0
Requires-Dist: nameparser>=1.1.3
Requires-Dist: fuzzywuzzy>=0.18.0
Requires-Dist: Levenshtein>=0.27.1
